<?xml version="1.0" encoding="UTF-8"?>
<Verzekeringmaatschapijen><Verzekeringmaatschappij kvkNr="12345678"><naam>naam</naam><telefoonNummer>233222</telefoonNummer><adres>adres</adres><plaats>plaats</plaats><iban>ibn</iban><postcode>postcode</postcode><btwNr>tt</btwNr></Verzekeringmaatschappij><Verzekeringmaatschappij kvkNr="12345679"><naam>naam</naam><telefoonNummer>233222</telefoonNummer><adres>adres</adres><plaats>plaats</plaats><iban>ibn</iban><postcode>postcode</postcode><btwNr>tt</btwNr></Verzekeringmaatschappij></Verzekeringmaatschapijen>