<?xml version="1.0" encoding="UTF-8"?>
<Facturen><Factuur nr="1"><naam>2013 - 1</naam><factuurDatum>Fri Mar 01 13:55:27 CET 2013</factuurDatum><vervalDatum>Mon Apr 01 13:55:27 CEST 2013</vervalDatum><vergoeding>2135.65</vergoeding><nietVergoeding>978.89</nietVergoeding><beginEigenrisico>0.0</beginEigenrisico><btwPercentage>21.0</btwPercentage><betalingsCondities>TODO: Betalingscondities navragen</betalingsCondities><betaald>false</betaald><klant>91214609</klant><verzekeringmaatschappij>VGZ</verzekeringmaatschappij><fysioPraktijk>1</fysioPraktijk></Factuur><Factuur nr="2"><naam>2013 - 2</naam><factuurDatum>Fri Mar 01 13:55:30 CET 2013</factuurDatum><vervalDatum>Mon Apr 01 13:55:30 CEST 2013</vervalDatum><vergoeding>686.6750000000001</vergoeding><nietVergoeding>608.63</nietVergoeding><beginEigenrisico>0.0</beginEigenrisico><btwPercentage>21.0</btwPercentage><betalingsCondities>TODO: Betalingscondities navragen</betalingsCondities><betaald>false</betaald><klant>91214609</klant><verzekeringmaatschappij>VGZ</verzekeringmaatschappij><fysioPraktijk>1</fysioPraktijk></Factuur><Factuur nr="3"><naam>2013 - 3</naam><factuurDatum>Fri Mar 01 13:55:34 CET 2013</factuurDatum><vervalDatum>Mon Apr 01 13:55:34 CEST 2013</vervalDatum><vergoeding>210.54</vergoeding><nietVergoeding>130.075</nietVergoeding><beginEigenrisico>0.0</beginEigenrisico><btwPercentage>21.0</btwPercentage><betalingsCondities>TODO: Betalingscondities navragen</betalingsCondities><betaald>false</betaald><klant>91214609</klant><verzekeringmaatschappij>VGZ</verzekeringmaatschappij><fysioPraktijk>1</fysioPraktijk></Factuur><Factuur nr="7"><naam>2013 - 7</naam><factuurDatum>Fri Mar 01 13:57:08 CET 2013</factuurDatum><vervalDatum>Mon Apr 01 13:57:08 CEST 2013</vervalDatum><vergoeding>47.485000000000014</vergoeding><nietVergoeding>1074.79</nietVergoeding><beginEigenrisico>350.0</beginEigenrisico><btwPercentage>21.0</btwPercentage><betalingsCondities>TODO: Betalingscondities navragen</betalingsCondities><betaald>false</betaald><klant>45560458</klant><verzekeringmaatschappij>FBTO</verzekeringmaatschappij><fysioPraktijk>1</fysioPraktijk></Factuur><Factuur nr="8"><naam>2014 - 8</naam><factuurDatum>Thu Nov 06 15:58:38 CET 2014</factuurDatum><vervalDatum>Sat Dec 06 15:58:38 CET 2014</vervalDatum><vergoeding>0.0</vergoeding><nietVergoeding>140.35999999999999</nietVergoeding><beginEigenrisico>0.0</beginEigenrisico><btwPercentage>21.0</btwPercentage><betalingsCondities>TODO: Betalingscondities navragen</betalingsCondities><betaald>false</betaald><klant>91214609</klant><verzekeringmaatschappij>VGZ</verzekeringmaatschappij><fysioPraktijk>1</fysioPraktijk></Factuur><Factuur nr="9"><naam>2014 - 9</naam><factuurDatum>Thu Nov 06 16:01:23 CET 2014</factuurDatum><vervalDatum>Sat Dec 06 16:01:23 CET 2014</vervalDatum><vergoeding>10.579999999999984</vergoeding><nietVergoeding>374.2</nietVergoeding><beginEigenrisico>350.0</beginEigenrisico><btwPercentage>21.0</btwPercentage><betalingsCondities>TODO: Betalingscondities navragen</betalingsCondities><betaald>true</betaald><klant>45321103</klant><verzekeringmaatschappij>VGZ</verzekeringmaatschappij><fysioPraktijk>1</fysioPraktijk></Factuur><Factuur nr="11"><naam>2014 - 11</naam><factuurDatum>Thu Nov 06 18:16:32 CET 2014</factuurDatum><vervalDatum>Sat Dec 06 18:16:32 CET 2014</vervalDatum><vergoeding>1244321.65</vergoeding><nietVergoeding>502336.33999999997</nietVergoeding><beginEigenrisico>0.0</beginEigenrisico><btwPercentage>21.0</btwPercentage><betalingsCondities>TODO: Betalingscondities navragen</betalingsCondities><betaald>false</betaald><klant>53070389</klant><verzekeringmaatschappij>Delta Lloyd</verzekeringmaatschappij><fysioPraktijk>1</fysioPraktijk></Factuur><Factuur nr="10"><naam>2014 - 10</naam><factuurDatum>Thu Nov 06 18:06:24 CET 2014</factuurDatum><vervalDatum>Sat Dec 06 18:06:24 CET 2014</vervalDatum><vergoeding>1253635.02</vergoeding><nietVergoeding>499320.415</nietVergoeding><beginEigenrisico>0.0</beginEigenrisico><btwPercentage>21.0</btwPercentage><betalingsCondities>TODO: Betalingscondities navragen</betalingsCondities><betaald>true</betaald><klant>53070389</klant><verzekeringmaatschappij>Delta Lloyd</verzekeringmaatschappij><fysioPraktijk>1</fysioPraktijk></Factuur><Factuur nr="12"><naam>2014 - 12</naam><factuurDatum>Thu Nov 06 18:26:16 CET 2014</factuurDatum><vervalDatum>Sat Dec 06 18:26:16 CET 2014</vervalDatum><vergoeding>87.725</vergoeding><nietVergoeding>419.87</nietVergoeding><beginEigenrisico>0.0</beginEigenrisico><btwPercentage>21.0</btwPercentage><betalingsCondities>TODO: Betalingscondities navragen</betalingsCondities><betaald>false</betaald><klant>45560458</klant><verzekeringmaatschappij>FBTO</verzekeringmaatschappij><fysioPraktijk>1</fysioPraktijk></Factuur><Factuur nr="13"><naam>2014 - 13</naam><factuurDatum>Thu Nov 06 18:26:39 CET 2014</factuurDatum><vervalDatum>Sat Dec 06 18:26:39 CET 2014</vervalDatum><vergoeding>177.87</vergoeding><nietVergoeding>603.79</nietVergoeding><beginEigenrisico>0.0</beginEigenrisico><btwPercentage>21.0</btwPercentage><betalingsCondities>TODO: Betalingscondities navragen</betalingsCondities><betaald>false</betaald><klant>45560458</klant><verzekeringmaatschappij>FBTO</verzekeringmaatschappij><fysioPraktijk>1</fysioPraktijk></Factuur><Factuur nr="14"><naam>2014 - 14</naam><factuurDatum>Thu Nov 06 18:27:02 CET 2014</factuurDatum><vervalDatum>Sat Dec 06 18:27:02 CET 2014</vervalDatum><vergoeding>186.945</vergoeding><nietVergoeding>649.77</nietVergoeding><beginEigenrisico>0.0</beginEigenrisico><btwPercentage>21.0</btwPercentage><betalingsCondities>TODO: Betalingscondities navragen</betalingsCondities><betaald>false</betaald><klant>45560458</klant><verzekeringmaatschappij>FBTO</verzekeringmaatschappij><fysioPraktijk>1</fysioPraktijk></Factuur><Factuur nr="15"><naam>2014 - 15</naam><factuurDatum>Thu Nov 06 18:27:24 CET 2014</factuurDatum><vervalDatum>Sat Dec 06 18:27:24 CET 2014</vervalDatum><vergoeding>226.26999999999998</vergoeding><nietVergoeding>442.86</nietVergoeding><beginEigenrisico>0.0</beginEigenrisico><btwPercentage>21.0</btwPercentage><betalingsCondities>TODO: Betalingscondities navragen</betalingsCondities><betaald>false</betaald><klant>45560458</klant><verzekeringmaatschappij>FBTO</verzekeringmaatschappij><fysioPraktijk>1</fysioPraktijk></Factuur><Factuur nr="16"><naam>2014 - 16</naam><factuurDatum>Thu Nov 06 18:27:49 CET 2014</factuurDatum><vervalDatum>Sat Dec 06 18:27:49 CET 2014</vervalDatum><vergoeding>226.26999999999998</vergoeding><nietVergoeding>454.96</nietVergoeding><beginEigenrisico>0.0</beginEigenrisico><btwPercentage>21.0</btwPercentage><betalingsCondities>TODO: Betalingscondities navragen</betalingsCondities><betaald>false</betaald><klant>45560458</klant><verzekeringmaatschappij>FBTO</verzekeringmaatschappij><fysioPraktijk>1</fysioPraktijk></Factuur><Factuur nr="18"><naam>2014 - 18</naam><factuurDatum>Thu Nov 06 18:29:30 CET 2014</factuurDatum><vervalDatum>Sat Dec 06 18:29:30 CET 2014</vervalDatum><vergoeding>33489.17</vergoeding><nietVergoeding>18237.12</nietVergoeding><beginEigenrisico>0.0</beginEigenrisico><btwPercentage>21.0</btwPercentage><betalingsCondities>TODO: Betalingscondities navragen</betalingsCondities><betaald>false</betaald><klant>91214609</klant><verzekeringmaatschappij>VGZ</verzekeringmaatschappij><fysioPraktijk>1</fysioPraktijk></Factuur><Factuur nr="19"><naam>2014 - 19</naam><factuurDatum>Thu Nov 06 18:29:54 CET 2014</factuurDatum><vervalDatum>Sat Dec 06 18:29:54 CET 2014</vervalDatum><vergoeding>34312.575</vergoeding><nietVergoeding>19102.875</nietVergoeding><beginEigenrisico>0.0</beginEigenrisico><btwPercentage>21.0</btwPercentage><betalingsCondities>TODO: Betalingscondities navragen</betalingsCondities><betaald>false</betaald><klant>91214609</klant><verzekeringmaatschappij>VGZ</verzekeringmaatschappij><fysioPraktijk>1</fysioPraktijk></Factuur><Factuur nr="20"><naam>2014 - 20</naam><factuurDatum>Thu Nov 06 18:30:18 CET 2014</factuurDatum><vervalDatum>Sat Dec 06 18:30:18 CET 2014</vervalDatum><vergoeding>36390.145</vergoeding><nietVergoeding>18336.34</nietVergoeding><beginEigenrisico>0.0</beginEigenrisico><btwPercentage>21.0</btwPercentage><betalingsCondities>TODO: Betalingscondities navragen</betalingsCondities><betaald>false</betaald><klant>91214609</klant><verzekeringmaatschappij>VGZ</verzekeringmaatschappij><fysioPraktijk>1</fysioPraktijk></Factuur><Factuur nr="21"><naam>2014 - 21</naam><factuurDatum>Thu Nov 06 18:30:42 CET 2014</factuurDatum><vervalDatum>Sat Dec 06 18:30:42 CET 2014</vervalDatum><vergoeding>34213.96</vergoeding><nietVergoeding>18254.665</nietVergoeding><beginEigenrisico>0.0</beginEigenrisico><btwPercentage>21.0</btwPercentage><betalingsCondities>TODO: Betalingscondities navragen</betalingsCondities><betaald>false</betaald><klant>91214609</klant><verzekeringmaatschappij>VGZ</verzekeringmaatschappij><fysioPraktijk>1</fysioPraktijk></Factuur><Factuur nr="6"><naam>2013 - 6</naam><factuurDatum>Fri Mar 01 13:56:36 CET 2013</factuurDatum><vervalDatum>Mon Apr 01 13:56:36 CEST 2013</vervalDatum><vergoeding>1277.7599999999998</vergoeding><nietVergoeding>339.405</nietVergoeding><beginEigenrisico>0.0</beginEigenrisico><btwPercentage>21.0</btwPercentage><betalingsCondities>TODO: Betalingscondities navragen</betalingsCondities><betaald>true</betaald><klant>53070389</klant><verzekeringmaatschappij>Delta Lloyd</verzekeringmaatschappij><fysioPraktijk>1</fysioPraktijk></Factuur><Factuur nr="5"><naam>2013 - 5</naam><factuurDatum>Fri Mar 01 13:56:32 CET 2013</factuurDatum><vervalDatum>Mon Apr 01 13:56:32 CEST 2013</vervalDatum><vergoeding>876.9399999999998</vergoeding><nietVergoeding>608.335</nietVergoeding><beginEigenrisico>350.0</beginEigenrisico><btwPercentage>21.0</btwPercentage><betalingsCondities>TODO: Betalingscondities navragen</betalingsCondities><betaald>true</betaald><klant>53070389</klant><verzekeringmaatschappij>Delta Lloyd</verzekeringmaatschappij><fysioPraktijk>1</fysioPraktijk></Factuur><Factuur nr="22"><naam>2014 - 22</naam><factuurDatum>Thu Nov 06 18:44:58 CET 2014</factuurDatum><vervalDatum>Sat Dec 06 18:44:58 CET 2014</vervalDatum><vergoeding>0.0</vergoeding><nietVergoeding>54942.47</nietVergoeding><beginEigenrisico>440.2</beginEigenrisico><btwPercentage>21.0</btwPercentage><betalingsCondities>TODO: Betalingscondities navragen</betalingsCondities><betaald>true</betaald><klant>1</klant><verzekeringmaatschappij>naam</verzekeringmaatschappij><fysioPraktijk>1</fysioPraktijk></Factuur><Factuur nr="23"><naam>2014 - 23</naam><factuurDatum>Thu Nov 06 22:04:11 CET 2014</factuurDatum><vervalDatum>Sat Dec 06 22:04:11 CET 2014</vervalDatum><vergoeding>0.0</vergoeding><nietVergoeding>50951.284999999996</nietVergoeding><beginEigenrisico>440.2</beginEigenrisico><btwPercentage>21.0</btwPercentage><betalingsCondities>TODO: Betalingscondities navragen</betalingsCondities><betaald>true</betaald><klant>1</klant><verzekeringmaatschappij>naam</verzekeringmaatschappij><fysioPraktijk>1</fysioPraktijk></Factuur><Factuur nr="17"><naam>2014 - 17</naam><factuurDatum>Thu Nov 06 18:29:06 CET 2014</factuurDatum><vervalDatum>Sat Dec 06 18:29:06 CET 2014</vervalDatum><vergoeding>35846.25</vergoeding><nietVergoeding>18574.71</nietVergoeding><beginEigenrisico>0.0</beginEigenrisico><btwPercentage>21.0</btwPercentage><betalingsCondities>TODO: Betalingscondities navragen</betalingsCondities><betaald>true</betaald><klant>91214609</klant><verzekeringmaatschappij>VGZ</verzekeringmaatschappij><fysioPraktijk>1</fysioPraktijk></Factuur><Factuur nr="24"><naam>2014 - 24</naam><factuurDatum>Thu Nov 06 22:06:10 CET 2014</factuurDatum><vervalDatum>Sat Dec 06 22:06:10 CET 2014</vervalDatum><vergoeding>34287.165</vergoeding><nietVergoeding>18838.489999999998</nietVergoeding><beginEigenrisico>0.0</beginEigenrisico><btwPercentage>21.0</btwPercentage><betalingsCondities>TODO: Betalingscondities navragen</betalingsCondities><betaald>true</betaald><klant>91214609</klant><verzekeringmaatschappij>VGZ</verzekeringmaatschappij><fysioPraktijk>1</fysioPraktijk></Factuur><Factuur nr="25"><naam>2014 - 25</naam><factuurDatum>Fri Nov 07 11:29:52 CET 2014</factuurDatum><vervalDatum>Sun Dec 07 11:29:52 CET 2014</vervalDatum><vergoeding>0.0</vergoeding><nietVergoeding>1441.11</nietVergoeding><beginEigenrisico>440.2</beginEigenrisico><btwPercentage>21.0</btwPercentage><betalingsCondities>TODO: Betalingscondities navragen</betalingsCondities><betaald>true</betaald><klant>1</klant><verzekeringmaatschappij>naam</verzekeringmaatschappij><fysioPraktijk>1</fysioPraktijk></Factuur><Factuur nr="27"><naam>2014 - 27</naam><factuurDatum>Fri Nov 07 11:41:07 CET 2014</factuurDatum><vervalDatum>Sun Dec 07 11:41:07 CET 2014</vervalDatum><vergoeding>0.0</vergoeding><nietVergoeding>1660.725</nietVergoeding><beginEigenrisico>440.2</beginEigenrisico><btwPercentage>21.0</btwPercentage><betalingsCondities>TODO: Betalingscondities navragen</betalingsCondities><betaald>true</betaald><klant>1</klant><verzekeringmaatschappij>naam</verzekeringmaatschappij><fysioPraktijk>1</fysioPraktijk></Factuur><Factuur nr="26"><naam>2014 - 26</naam><factuurDatum>Fri Nov 07 11:32:31 CET 2014</factuurDatum><vervalDatum>Sun Dec 07 11:32:31 CET 2014</vervalDatum><vergoeding>0.0</vergoeding><nietVergoeding>2719.475</nietVergoeding><beginEigenrisico>440.2</beginEigenrisico><btwPercentage>21.0</btwPercentage><betalingsCondities>TODO: Betalingscondities navragen</betalingsCondities><betaald>true</betaald><klant>1</klant><verzekeringmaatschappij>naam</verzekeringmaatschappij><fysioPraktijk>1</fysioPraktijk></Factuur><Factuur nr="29"><naam>2014 - 29</naam><factuurDatum>Fri Nov 07 11:45:13 CET 2014</factuurDatum><vervalDatum>Sun Dec 07 11:45:13 CET 2014</vervalDatum><vergoeding>0.0</vergoeding><nietVergoeding>349.69</nietVergoeding><beginEigenrisico>440.2</beginEigenrisico><btwPercentage>21.0</btwPercentage><betalingsCondities>TODO: Betalingscondities navragen</betalingsCondities><betaald>true</betaald><klant>1</klant><verzekeringmaatschappij>naam</verzekeringmaatschappij><fysioPraktijk>1</fysioPraktijk></Factuur><Factuur nr="28"><naam>2014 - 28</naam><factuurDatum>Fri Nov 07 11:43:24 CET 2014</factuurDatum><vervalDatum>Sun Dec 07 11:43:24 CET 2014</vervalDatum><vergoeding>0.0</vergoeding><nietVergoeding>1029.71</nietVergoeding><beginEigenrisico>440.2</beginEigenrisico><btwPercentage>21.0</btwPercentage><betalingsCondities>TODO: Betalingscondities navragen</betalingsCondities><betaald>true</betaald><klant>1</klant><verzekeringmaatschappij>naam</verzekeringmaatschappij><fysioPraktijk>1</fysioPraktijk></Factuur><Factuur nr="30"><naam>2014 - 30</naam><factuurDatum>Fri Nov 07 11:46:05 CET 2014</factuurDatum><vervalDatum>Sun Dec 07 11:46:05 CET 2014</vervalDatum><vergoeding>0.0</vergoeding><nietVergoeding>2289.3199999999997</nietVergoeding><beginEigenrisico>440.2</beginEigenrisico><btwPercentage>21.0</btwPercentage><betalingsCondities>TODO: Betalingscondities navragen</betalingsCondities><betaald>true</betaald><klant>1</klant><verzekeringmaatschappij>naam</verzekeringmaatschappij><fysioPraktijk>1</fysioPraktijk></Factuur><Factuur nr="31"><naam>2014 - 31</naam><factuurDatum>Fri Nov 07 11:46:45 CET 2014</factuurDatum><vervalDatum>Sun Dec 07 11:46:45 CET 2014</vervalDatum><vergoeding>0.0</vergoeding><nietVergoeding>1162.205</nietVergoeding><beginEigenrisico>440.2</beginEigenrisico><btwPercentage>21.0</btwPercentage><betalingsCondities>TODO: Betalingscondities navragen</betalingsCondities><betaald>true</betaald><klant>1</klant><verzekeringmaatschappij>naam</verzekeringmaatschappij><fysioPraktijk>1</fysioPraktijk></Factuur><Factuur nr="32"><naam>2014 - 32</naam><factuurDatum>Fri Nov 07 11:47:33 CET 2014</factuurDatum><vervalDatum>Sun Dec 07 11:47:33 CET 2014</vervalDatum><vergoeding>0.0</vergoeding><nietVergoeding>2158.035</nietVergoeding><beginEigenrisico>440.2</beginEigenrisico><btwPercentage>21.0</btwPercentage><betalingsCondities>TODO: Betalingscondities navragen</betalingsCondities><betaald>true</betaald><klant>1</klant><verzekeringmaatschappij>naam</verzekeringmaatschappij><fysioPraktijk>1</fysioPraktijk></Factuur><Factuur nr="33"><naam>2014 - 33</naam><factuurDatum>Mon Nov 10 13:12:31 CET 2014</factuurDatum><vervalDatum>Wed Dec 10 13:12:31 CET 2014</vervalDatum><vergoeding>0.0</vergoeding><nietVergoeding>425.315</nietVergoeding><beginEigenrisico>440.2</beginEigenrisico><btwPercentage>21.0</btwPercentage><betalingsCondities>TODO: Betalingscondities navragen</betalingsCondities><betaald>false</betaald><klant>1</klant><verzekeringmaatschappij>naam</verzekeringmaatschappij><fysioPraktijk>1</fysioPraktijk></Factuur><Factuur nr="34"><naam>2014 - 34</naam><factuurDatum>Mon Nov 10 13:14:47 CET 2014</factuurDatum><vervalDatum>Wed Dec 10 13:14:47 CET 2014</vervalDatum><vergoeding>0.0</vergoeding><nietVergoeding>1577.84</nietVergoeding><beginEigenrisico>440.2</beginEigenrisico><btwPercentage>21.0</btwPercentage><betalingsCondities>TODO: Betalingscondities navragen</betalingsCondities><betaald>false</betaald><klant>1</klant><verzekeringmaatschappij>naam</verzekeringmaatschappij><fysioPraktijk>1</fysioPraktijk></Factuur><Factuur nr="35"><naam>2014 - 35</naam><factuurDatum>Mon Nov 10 13:16:55 CET 2014</factuurDatum><vervalDatum>Wed Dec 10 13:16:55 CET 2014</vervalDatum><vergoeding>0.0</vergoeding><nietVergoeding>1635.315</nietVergoeding><beginEigenrisico>440.2</beginEigenrisico><btwPercentage>21.0</btwPercentage><betalingsCondities>TODO: Betalingscondities navragen</betalingsCondities><betaald>false</betaald><klant>1</klant><verzekeringmaatschappij>naam</verzekeringmaatschappij><fysioPraktijk>1</fysioPraktijk></Factuur><Factuur nr="36"><naam>2014 - 36</naam><factuurDatum>Mon Nov 10 13:19:01 CET 2014</factuurDatum><vervalDatum>Wed Dec 10 13:19:01 CET 2014</vervalDatum><vergoeding>0.0</vergoeding><nietVergoeding>943.8</nietVergoeding><beginEigenrisico>440.2</beginEigenrisico><btwPercentage>21.0</btwPercentage><betalingsCondities>TODO: Betalingscondities navragen</betalingsCondities><betaald>false</betaald><klant>1</klant><verzekeringmaatschappij>naam</verzekeringmaatschappij><fysioPraktijk>1</fysioPraktijk></Factuur><Factuur nr="37"><naam>2014 - 37</naam><factuurDatum>Mon Nov 10 13:28:56 CET 2014</factuurDatum><vervalDatum>Wed Dec 10 13:28:56 CET 2014</vervalDatum><vergoeding>0.0</vergoeding><nietVergoeding>413.82</nietVergoeding><beginEigenrisico>440.2</beginEigenrisico><btwPercentage>21.0</btwPercentage><betalingsCondities>TODO: Betalingscondities navragen</betalingsCondities><betaald>false</betaald><klant>1</klant><verzekeringmaatschappij>naam</verzekeringmaatschappij><fysioPraktijk>1</fysioPraktijk></Factuur><Factuur nr="38"><naam>2014 - 38</naam><factuurDatum>Mon Nov 10 13:34:49 CET 2014</factuurDatum><vervalDatum>Wed Dec 10 13:34:49 CET 2014</vervalDatum><vergoeding>0.0</vergoeding><nietVergoeding>96.8</nietVergoeding><beginEigenrisico>440.2</beginEigenrisico><btwPercentage>21.0</btwPercentage><betalingsCondities>TODO: Betalingscondities navragen</betalingsCondities><betaald>false</betaald><klant>1</klant><verzekeringmaatschappij>naam</verzekeringmaatschappij><fysioPraktijk>1</fysioPraktijk></Factuur><Factuur nr="40"><naam>2014 - 40</naam><factuurDatum>Thu Nov 13 11:36:10 CET 2014</factuurDatum><vervalDatum>Sat Dec 13 11:36:10 CET 2014</vervalDatum><vergoeding>39.325</vergoeding><nietVergoeding>314.59999999999997</nietVergoeding><beginEigenrisico>0.0</beginEigenrisico><btwPercentage>21.0</btwPercentage><betalingsCondities>TODO: Betalingscondities navragen</betalingsCondities><betaald>true</betaald><klant>51693959</klant><verzekeringmaatschappij>Centraal Beheer Achmea</verzekeringmaatschappij><fysioPraktijk>1</fysioPraktijk></Factuur><Factuur nr="42"><naam>2014 - 42</naam><factuurDatum>Thu Nov 13 12:18:05 CET 2014</factuurDatum><vervalDatum>Sat Dec 13 12:18:05 CET 2014</vervalDatum><vergoeding>0.0</vergoeding><nietVergoeding>1818.0249999999999</nietVergoeding><beginEigenrisico>440.2</beginEigenrisico><btwPercentage>21.0</btwPercentage><betalingsCondities>TODO: Betalingscondities navragen</betalingsCondities><betaald>false</betaald><klant>1</klant><verzekeringmaatschappij>naam</verzekeringmaatschappij><fysioPraktijk>1</fysioPraktijk></Factuur><Factuur nr="44"><naam>2014 - 44</naam><factuurDatum>Thu Nov 13 12:40:49 CET 2014</factuurDatum><vervalDatum>Sat Dec 13 12:40:49 CET 2014</vervalDatum><vergoeding>0.0</vergoeding><nietVergoeding>90.145</nietVergoeding><beginEigenrisico>440.2</beginEigenrisico><btwPercentage>21.0</btwPercentage><betalingsCondities>TODO: Betalingscondities navragen</betalingsCondities><betaald>false</betaald><klant>1</klant><verzekeringmaatschappij>naam</verzekeringmaatschappij><fysioPraktijk>1</fysioPraktijk></Factuur><Factuur nr="4"><naam>naam</naam><factuurDatum>Thu Nov 13 12:40:49 CET 2014</factuurDatum><vervalDatum>Thu Nov 13 12:40:49 CET 2014</vervalDatum><vergoeding>100.0</vergoeding><nietVergoeding>200.0</nietVergoeding><beginEigenrisico>300.0</beginEigenrisico><btwPercentage>21.0</btwPercentage><betalingsCondities>geen</betalingsCondities><betaald>true</betaald><klant>4</klant><verzekeringmaatschappij>verzekeringmaatschappij</verzekeringmaatschappij><fysioPraktijk>2</fysioPraktijk></Factuur><Factuur nr="45"><naam>2015 - 45</naam><factuurDatum>Mon Apr 20 11:22:55 CEST 2015</factuurDatum><vervalDatum>Wed May 20 11:22:55 CEST 2015</vervalDatum><vergoeding>1099.8899999999999</vergoeding><nietVergoeding>263.78</nietVergoeding><beginEigenrisico>0.0</beginEigenrisico><btwPercentage>21.0</btwPercentage><betalingsCondities>TODO: Betalingscondities navragen</betalingsCondities><betaald>false</betaald><klant>53070389</klant><verzekeringmaatschappij>Delta Lloyd</verzekeringmaatschappij><fysioPraktijk>1</fysioPraktijk></Factuur><Factuur nr="46"><naam>2015 - 46</naam><factuurDatum>Mon Apr 20 11:25:26 CEST 2015</factuurDatum><vervalDatum>Wed May 20 11:25:26 CEST 2015</vervalDatum><vergoeding>177.87</vergoeding><nietVergoeding>692.725</nietVergoeding><beginEigenrisico>0.0</beginEigenrisico><btwPercentage>21.0</btwPercentage><betalingsCondities>TODO: Betalingscondities navragen</betalingsCondities><betaald>true</betaald><klant>49165590</klant><verzekeringmaatschappij>FBTO</verzekeringmaatschappij><fysioPraktijk>1</fysioPraktijk></Factuur><Factuur nr="41"><naam>2014 - 41</naam><factuurDatum>Thu Nov 13 12:16:32 CET 2014</factuurDatum><vervalDatum>Sat Dec 13 12:16:32 CET 2014</vervalDatum><vergoeding>93.46499999999997</vergoeding><nietVergoeding>1125.0049999999999</nietVergoeding><beginEigenrisico>350.0</beginEigenrisico><btwPercentage>21.0</btwPercentage><betalingsCondities>TODO: Betalingscondities navragen</betalingsCondities><betaald>true</betaald><klant>49165590</klant><verzekeringmaatschappij>FBTO</verzekeringmaatschappij><fysioPraktijk>1</fysioPraktijk></Factuur><Factuur nr="47"><naam>2015 - 47</naam><factuurDatum>Mon Apr 20 13:39:28 CEST 2015</factuurDatum><vervalDatum>Wed May 20 13:39:28 CEST 2015</vervalDatum><vergoeding>780.4499999999999</vergoeding><nietVergoeding>1703.075</nietVergoeding><beginEigenrisico>0.0</beginEigenrisico><btwPercentage>21.0</btwPercentage><betalingsCondities>TODO: Betalingscondities navragen</betalingsCondities><betaald>true</betaald><klant>45560458</klant><verzekeringmaatschappij>FBTO</verzekeringmaatschappij><fysioPraktijk>1</fysioPraktijk></Factuur><Factuur nr="43"><naam>2014 - 43</naam><factuurDatum>Thu Nov 13 12:29:04 CET 2014</factuurDatum><vervalDatum>Sat Dec 13 12:29:04 CET 2014</vervalDatum><vergoeding>268.015</vergoeding><nietVergoeding>934.7249999999999</nietVergoeding><beginEigenrisico>0.0</beginEigenrisico><btwPercentage>21.0</btwPercentage><betalingsCondities>TODO: Betalingscondities navragen</betalingsCondities><betaald>true</betaald><klant>51693959</klant><verzekeringmaatschappij>Centraal Beheer Achmea</verzekeringmaatschappij><fysioPraktijk>1</fysioPraktijk></Factuur><Factuur nr="39"><naam>2014 - 39</naam><factuurDatum>Thu Nov 13 11:34:26 CET 2014</factuurDatum><vervalDatum>Sat Dec 13 11:34:26 CET 2014</vervalDatum><vergoeding>230.19499999999994</vergoeding><nietVergoeding>1465.015</nietVergoeding><beginEigenrisico>350.0</beginEigenrisico><btwPercentage>21.0</btwPercentage><betalingsCondities>TODO: Betalingscondities navragen</betalingsCondities><betaald>true</betaald><klant>51693959</klant><verzekeringmaatschappij>Centraal Beheer Achmea</verzekeringmaatschappij><fysioPraktijk>1</fysioPraktijk></Factuur><Factuur nr="48"><naam>2015 - 48</naam><factuurDatum>Mon Apr 20 14:47:46 CEST 2015</factuurDatum><vervalDatum>Wed May 20 14:47:46 CEST 2015</vervalDatum><vergoeding>0.0</vergoeding><nietVergoeding>35.695</nietVergoeding><beginEigenrisico>0.0</beginEigenrisico><btwPercentage>21.0</btwPercentage><betalingsCondities>TODO: Betalingscondities navragen</betalingsCondities><betaald>true</betaald><klant>51693959</klant><verzekeringmaatschappij>Centraal Beheer Achmea</verzekeringmaatschappij><fysioPraktijk>1</fysioPraktijk></Factuur><Factuur nr="49"><naam>2015 - 49</naam><factuurDatum>Mon Apr 20 14:48:31 CEST 2015</factuurDatum><vervalDatum>Wed May 20 14:48:31 CEST 2015</vervalDatum><vergoeding>235.34500000000003</vergoeding><nietVergoeding>682.44</nietVergoeding><beginEigenrisico>0.0</beginEigenrisico><btwPercentage>21.0</btwPercentage><betalingsCondities>TODO: Betalingscondities navragen</betalingsCondities><betaald>true</betaald><klant>51693959</klant><verzekeringmaatschappij>Centraal Beheer Achmea</verzekeringmaatschappij><fysioPraktijk>1</fysioPraktijk></Factuur></Facturen>